README.md
setup.cfg
setup.py
gencharts/__init__.py
gencharts.egg-info/PKG-INFO
gencharts.egg-info/SOURCES.txt
gencharts.egg-info/dependency_links.txt
gencharts.egg-info/not-zip-safe
gencharts.egg-info/requires.txt
gencharts.egg-info/top_level.txt