Metadata-Version: 1.1
Name: gencharts
Version: 0.5
Summary: Generate html charts with Altair
Home-page: https://github.com/synw/gencharts
Author: synw
Author-email: synwe@yahoo.com
License: UNKNOWN
Download-URL: https://github.com/synw/gencharts/releases/tag/0.5
Keywords: errors,error_handling
Platform: UNKNOWN
Classifier: Development Status :: 3 - Alpha
Classifier: Intended Audience :: Developers
Classifier: License :: OSI Approved :: MIT License
Classifier: Programming Language :: Python :: 3.5
